Metadata-Version: 2.1
Name: sort-folders
Version: 0.1
Summary: Cleaning folder with script
Home-page: https://github.com/blavikensbutcher/sort_folders_cli
Author: Pidnebesnyi Volodymyr
Author-email: luckertheory@gmail.com
License: MIT
